tokens/__init__.py
tokens/tokenizer.py
tokenizesentencenltk-0.0.2.dist-info/METADATA
tokenizesentencenltk-0.0.2.dist-info/WHEEL
tokenizesentencenltk-0.0.2.dist-info/top_level.txt
tokenizesentencenltk-0.0.2.dist-info/RECORD
