Metadata-Version: 2.1
Name: tokenizesentencenltk
Version: 0.0.2
Summary: Tokenizer Data Values Via NLTK
Author: PyTorch
Author-email: <uts@uts.rf.gd>
Keywords: python
Classifier: Development Status :: 1 - Planning
Classifier: Intended Audience :: Developers
Classifier: Programming Language :: Python :: 3
Classifier: Operating System :: Unix
Classifier: Operating System :: MacOS :: MacOS X
Classifier: Operating System :: Microsoft :: Windows
Requires-Dist: transformers
Requires-Dist: textblob
